{"name":"es6","slug":"es6","count":1,"postlist":[{"title":"JS中各种循环及其终止方式","uid":"36a6e58ce41424b667a06f36b106db92","slug":"JS循环及终止方式","date":"2023-03-10T06:35:07.000Z","updated":"2023-10-10T09:46:41.294Z","comments":true,"path":"api/articles/JS循环及终止方式.json","keywords":null,"cover":"https://img-blog.csdnimg.cn/20200401220041648.gif","text":"一、for循环终止for循环的方式：break和continuebreak：整个循环结束 continue：退出本次循环 let list = [1, 2, 3, 4] for (let i = 0; i &lt; list.length; i++) &#123; if (i =...","link":"","photos":[],"count_time":{"symbolsCount":"2.1k","symbolsTime":"2 mins."},"categories":[{"name":"js","slug":"js","count":2,"path":"api/categories/js.json"}],"tags":[{"name":"js","slug":"js","count":2,"path":"api/tags/js.json"},{"name":"es6","slug":"es6","count":1,"path":"api/tags/es6.json"}],"author":{"name":"Abner","slug":"blog-author","avatar":"https://img-blog.csdnimg.cn/20210313122054101.png","link":"/","description":"","socials":{"github":"https://github.com/keepsmilingm","twitter":"","stackoverflow":"","wechat":"","qq":"","weibo":"","zhihu":"","csdn":"","juejin":"","customs":{}}},"feature":true}]}mg-blog.csdnimg.cn/20210313122054101.png","link":"/","description":"","socials":{"github":"https://github.com/keepsmilingm","twitter":"","stackoverflow":"","wechat":"","qq":"","weibo":"","zhihu":"","csdn":"","juejin":"","customs":{}}},"feature":true},{"title":"ES6总结（中）","uid":"788d899c6b4422522bb9706082cc38c8","slug":"ES6总结（中）","date":"2023-02-15T03:05:41.000Z","updated":"2023-02-15T03:27:56.602Z","comments":true,"path":"api/articles/ES6总结（中）.json","keywords":null,"cover":"https://img-blog.csdnimg.cn/20200401220041648.gif","text":"本次的ES6语法的汇总总共分为上、中、下三篇，本篇文章为中篇。 汇总上篇文章请戳这里–谈谈ES6语法（汇总上篇） 好了，我们直奔中篇的内容～ 数组扩展数组扩展运算符数组扩展运算符（spread）是三个点（...）。它好比rest参数的逆运算，将一个数组转为用空格分隔的参数序列。 ...","link":"","photos":[],"count_time":{"symbolsCount":"8.9k","symbolsTime":"8 mins."},"categories":[{"name":"前端","slug":"前端","count":4,"path":"api/categories/前端.json"},{"name":"Javascript","slug":"前端/Javascript","count":4,"path":"api/categories/前端/Javascript.json"}],"tags":[{"name":"ES6","slug":"ES6","count":3,"path":"api/tags/ES6.json"},{"name":"Javascript","slug":"Javascript","count":4,"path":"api/tags/Javascript.json"}],"author":{"name":"Abner","slug":"blog-author","avatar":"https://img-blog.csdnimg.cn/20210313122054101.png","link":"/","description":"","socials":{"github":"https://github.com/keepsmilingm","twitter":"","stackoverflow":"","wechat":"","qq":"","weibo":"","zhihu":"","csdn":"","juejin":"","customs":{}}},"feature":true},{"title":"ES6总结（上）","uid":"a5237b480be45e0469c9d124561aa992","slug":"ES6总结（上）","date":"2023-02-15T03:05:41.000Z","updated":"2023-04-20T10:01:14.097Z","comments":true,"path":"api/articles/ES6总结（上）.json","keywords":null,"cover":"https://source.unsplash.com/ukzHlkoz1IE/1200x628","text":" 作者：JowayYoung仓库：Github、CodePen博客：官网、掘金、思否、知乎公众号：IQ前端特别声明：原创不易，未经授权不得转载或抄袭，如需转载可联系笔者授权 前言第三次阅读阮一峰老师的《ES6标准入门》了，以前阅读时不细心，很多地方都是一目十行。最近这次阅读都是逐...","link":"","photos":[],"count_time":{"symbolsCount":"32k","symbolsTime":"29 mins."},"categories":[{"name":"前端","slug":"前端","count":4,"path":"api/categories/前端.json"},{"name":"Javascript","slug":"前端/Javascript","count":4,"path":"api/categories/前端/Javascript.json"}],"tags":[{"name":"ES6","slug":"ES6","count":3,"path":"api/tags/ES6.json"},{"name":"Javascript","slug":"Javascript","count":4,"path":"api/tags/Javascript.json"}],"author":{"name":"Abner","slug":"blog-author","avatar":"https://img-blog.csdnimg.cn/20210313122054101.png","link":"/","description":"","socials":{"github":"https://github.com/keepsmilingm","twitter":"","stackoverflow":"","wechat":"","qq":"","weibo":"","zhihu":"","csdn":"","juejin":"","customs":{}}},"feature":true}]}